<?xml version="1.0" encoding="utf-8" ?><dwsync><file name="images.ctp~" server="ftp.harmonydesigns.com" local="3474904368" remote="323953104236540864" Dst="-1" /><file name="nav.ctp" server="ftp.harmonydesigns.com" local="3474904368" remote="323953104277580864" Dst="-1" /><file name="images.ctp" server="ftp.harmonydesigns.com" local="3474904368" remote="323953104277580864" Dst="-1" /><file name="pricing_chart.ctp" server="ftp.harmonydesigns.com" local="3474904368" remote="323953104277580864" Dst="-1" /><file name="nav.ctp~" server="ftp.harmonydesigns.com" local="3474904369" remote="323953104249328064" Dst="-1" /><file name="pricing_list.ctp" server="ftp.harmonydesigns.com" local="3474904369" remote="323953104277580864" Dst="-1" /><file name="pricing_list.ctp.bak" server="ftp.harmonydesigns.com" local="3474904369" remote="323953104277580864" Dst="-1" /><file name="sample_gallery.ctp" server="ftp.harmonydesigns.com" local="3474904369" remote="323953104277580864" Dst="-1" /><file name="product_diagram.ctp" server="ftp.harmonydesigns.com" local="3474904369" remote="323953104277580864" Dst="-1" /></dwsync>